{"cameraMode":{"drawMode":0,"name":"Shaded","section":"Shading Mode"},"sceneLighting":true,"audioPlay":false,"sceneViewState":{"m_AlwaysRefresh":false,"showFog":true,"showSkybox":true,"showFlares":true,"showImageEffects":true,"showParticleSystems":true,"showVisualEffectGraphs":true,"m_FxEnabled":true},"in2DMode":false,"pivot":{"x":12.925543785095215,"y":-45.102413177490237,"z":40.87590789794922},"rotation":{"x":-0.34845563769340517,"y":-0.1420457661151886,"z":0.05355839058756828,"w":-0.9248998761177063},"size":39.51441192626953,"orthographic":false}